CHANGES.rst
CONTRIBUTORS.rst
DEVELOP.rst
LICENSE.GPL
LICENSE.rst
MANIFEST.in
README.rst
setup.cfg
setup.py
docs/Makefile
docs/conf.py
docs/creategroup.rst
docs/createuser.rst
docs/index.rst
docs/updategroupproperty.rst
docs/updateuserproperty.rst
export_scripts/plone2.0_export.py
src/collective/__init__.py
src/collective.blueprint.usersandgroups.egg-info/PKG-INFO
src/collective.blueprint.usersandgroups.egg-info/SOURCES.txt
src/collective.blueprint.usersandgroups.egg-info/dependency_links.txt
src/collective.blueprint.usersandgroups.egg-info/entry_points.txt
src/collective.blueprint.usersandgroups.egg-info/namespace_packages.txt
src/collective.blueprint.usersandgroups.egg-info/not-zip-safe
src/collective.blueprint.usersandgroups.egg-info/requires.txt
src/collective.blueprint.usersandgroups.egg-info/top_level.txt
src/collective/blueprint/__init__.py
src/collective/blueprint/usersandgroups/__init__.py
src/collective/blueprint/usersandgroups/blueprint.py
src/collective/blueprint/usersandgroups/configure.zcml
src/collective/blueprint/usersandgroups/testing.py
src/collective/blueprint/usersandgroups/tests/__init__.py
src/collective/blueprint/usersandgroups/tests/test_blueprint.py