Metadata-Version: 2.1
Name: collective.blueprint.usersandgroups
Version: 0.3.1
Summary: transmogrifier blueprints for importing users and groups into plone
Home-page: https://github.com/collective/collective.blueprint.usersandgroups
Author: Rok Garbas
Author-email: rok@garbas.si
License: GPL version 2
Project-URL: PyPI, https://pypi.python.org/pypi/collective.blueprint.usersandgroups
Project-URL: Source, https://github.com/collective/collective.blueprint.usersandgroups
Project-URL: Tracker, https://github.com/collective/collective.blueprint.usersandgroups/issues
Keywords: plone transmogrifier blueprint user group
Platform: UNKNOWN
Classifier: Development Status :: 5 - Production/Stable
Classifier: Environment :: Web Environment
Classifier: Framework :: Plone
Classifier: Framework :: Plone :: Addon
Classifier: Framework :: Plone :: 4.3
Classifier: Framework :: Plone :: 5.1
Classifier: Framework :: Plone :: 5.2
Classifier: Programming Language :: Python
Classifier: Programming Language :: Python :: 2.7
Classifier: Programming Language :: Python :: 3.7
Classifier: Programming Language :: Python :: 3.8
Classifier: Operating System :: OS Independent
Classifier: License :: OSI Approved :: GNU General Public License v2 (GPLv2)
Requires-Python: >=2.7
Provides-Extra: test
License-File: LICENSE.GPL
License-File: LICENSE.rst
